bmi_nwis/__init__.py
bmi_nwis/_version.py
bmi_nwis/bmi.py
bmi_nwis/utils.py
bmi_nwis-0.1.dist-info/LICENSE.txt
bmi_nwis-0.1.dist-info/METADATA
bmi_nwis-0.1.dist-info/WHEEL
bmi_nwis-0.1.dist-info/top_level.txt
bmi_nwis-0.1.dist-info/RECORD
