Metadata-Version: 2.1
Name: bmi-nwis
Version: 0.1
Summary: BMI implementation for datasets from National Water Information System https://waterdata.usgs.gov/nwis?
Home-page: http://csdms.colorado.edu
Author: Tian Gan
Author-email: jamy127@foxmail.com
License: UNKNOWN
Platform: UNKNOWN
Requires-Dist: bmipy
Requires-Dist: numpy
Requires-Dist: pyyaml
Requires-Dist: xarray
Requires-Dist: dataretrieval
Requires-Dist: cftime
Requires-Dist: pandas
Requires-Dist: requests
Requires-Dist: netcdf4
